{
  "annotations": {
    "list": [
      {
        "builtIn": 1,
        "datasource": {
          "type": "datasource",
          "uid": "grafana"
        },
        "enable": true,
        "hide": true,
        "iconColor": "rgba(0, 211, 255, 1)",
        "name": "Annotations & Alerts",
        "type": "dashboard"
      }
    ]
  },
  "editable": true,
  "fiscalYearStartMonth": 0,
  "graphTooltip": 0,
  "id": 488,
  "links": [],
  "panels": [
    {
      "collapsed": false,
      "datasource": {
        "uid": "$datasource"
      },
      "gridPos": {
        "h": 1,
        "w": 24,
        "x": 0,
        "y": 0
      },
      "id": 14,
      "targets": [
        {
          "datasource": {
            "uid": "$datasource"
          },
          "refId": "A"
        }
      ],
      "title": "Overall status",
      "type": "row"
    },
    {
      "datasource": {
        "uid": "$datasource"
      },
      "description": "KMM Status shows current state of kafka-mirror-maker. It can be UP,  DEGRADED, FAILED. ",
      "fieldConfig": {
        "defaults": {
          "mappings": [
            {
              "options": {
                "match": "null",
                "result": {
                  "text": "N/A"
                }
              },
              "type": "special"
            },
            {
              "options": {
                "0": {
                  "text": "UP"
                }
              },
              "type": "value"
            },
            {
              "options": {
                "1": {
                  "text": "DEGRADED"
                }
              },
              "type": "value"
            },
            {
              "options": {
                "2": {
                  "text": "FAILED"
                }
              },
              "type": "value"
            }
          ],
          "thresholds": {
            "mode": "absolute",
            "steps": [
              {
                "color": "#299c46",
                "value": null
              },
              {
                "color": "#FF9830",
                "value": 1
              },
              {
                "color": "#C4162A",
                "value": 2
              }
            ]
          },
          "unit": "none"
        },
        "overrides": []
      },
      "gridPos": {
        "h": 9,
        "w": 9,
        "x": 0,
        "y": 1
      },
      "id": 2,
      "maxDataPoints": 100,
      "options": {
        "colorMode": "value",
        "graphMode": "none",
        "justifyMode": "auto",
        "orientation": "horizontal",
        "percentChangeColorMode": "standard",
        "reduceOptions": {
          "calcs": [
            "lastNotNull"
          ],
          "fields": "",
          "values": false
        },
        "showPercentChange": false,
        "textMode": "auto",
        "wideLayout": true
      },
      "pluginVersion": "11.2.1",
      "targets": [
        {
          "datasource": {
            "uid": "$datasource"
          },
          "expr": "max(kmm_health_status_code{project_name=~\"$project\" ,cluster=\"$cluster\"})",
          "groupBy": [
            {
              "params": [
                "$__interval"
              ],
              "type": "time"
            },
            {
              "params": [
                "null"
              ],
              "type": "fill"
            }
          ],
          "measurement": "kmm_health",
          "orderByTime": "ASC",
          "policy": "default",
          "rawQuery": true,
          "refId": "A",
          "resultFormat": "time_series",
          "select": [
            [
              {
                "params": [
                  "status_code"
                ],
                "type": "field"
              }
            ]
          ],
          "tags": [
            {
              "key": "project_name",
              "operator": "=~",
              "value": "/^$project$/"
            }
          ]
        }
      ],
      "title": "KMM Status",
      "type": "stat"
    },
    {
      "datasource": {
        "uid": "$datasource"
      },
      "description": "Node Status shows the amount of alive and failed instances.",
      "fieldConfig": {
        "defaults": {
          "color": {
            "mode": "palette-classic"
          },
          "custom": {
            "axisBorderShow": false,
            "axisCenteredZero": false,
            "axisColorMode": "text",
            "axisLabel": "",
            "axisPlacement": "auto",
            "barAlignment": 0,
            "barWidthFactor": 0.6,
            "drawStyle": "line",
            "fillOpacity": 10,
            "gradientMode": "none",
            "hideFrom": {
              "legend": false,
              "tooltip": false,
              "viz": false
            },
            "insertNulls": false,
            "lineInterpolation": "linear",
            "lineWidth": 1,
            "pointSize": 5,
            "scaleDistribution": {
              "type": "linear"
            },
            "showPoints": "never",
            "spanNulls": true,
            "stacking": {
              "group": "A",
              "mode": "none"
            },
            "thresholdsStyle": {
              "mode": "off"
            }
          },
          "decimals": 0,
          "mappings": [],
          "thresholds": {
            "mode": "absolute",
            "steps": [
              {
                "color": "green",
                "value": null
              },
              {
                "color": "red",
                "value": 80
              }
            ]
          },
          "unit": "short"
        },
        "overrides": [
          {
            "matcher": {
              "id": "byRegexp",
              "options": "/DOWN$/"
            },
            "properties": [
              {
                "id": "color",
                "value": {
                  "fixedColor": "#C4162A",
                  "mode": "fixed"
                }
              },
              {
                "id": "custom.fillOpacity",
                "value": 20
              }
            ]
          }
        ]
      },
      "gridPos": {
        "h": 9,
        "w": 15,
        "x": 9,
        "y": 1
      },
      "id": 4,
      "options": {
        "legend": {
          "calcs": [
            "lastNotNull"
          ],
          "displayMode": "table",
          "placement": "right",
          "showLegend": true
        },
        "tooltip": {
          "mode": "multi",
          "sort": "none"
        }
      },
      "targets": [
        {
          "alias": "UP",
          "datasource": {
            "uid": "$datasource"
          },
          "expr": "min(kmm_health_alive_nodes{project_name=~\"$project\" ,cluster=\"$cluster\"})",
          "groupBy": [
            {
              "params": [
                "$__interval"
              ],
              "type": "time"
            },
            {
              "params": [
                "null"
              ],
              "type": "fill"
            }
          ],
          "legendFormat": "alive nodes",
          "measurement": "kmm_health",
          "orderByTime": "ASC",
          "policy": "default",
          "rawQuery": true,
          "refId": "A",
          "resultFormat": "time_series",
          "select": [
            [
              {
                "params": [
                  "alive_nodes"
                ],
                "type": "field"
              }
            ]
          ],
          "tags": [
            {
              "key": "project_name",
              "operator": "=~",
              "value": "/^$project$/"
            }
          ]
        },
        {
          "alias": "DOWN",
          "datasource": {
            "uid": "$datasource"
          },
          "expr": "min(kmm_health_failed_nodes{project_name=~\"$project\" ,cluster=\"$cluster\"})",
          "groupBy": [
            {
              "params": [
                "$__interval"
              ],
              "type": "time"
            },
            {
              "params": [
                "null"
              ],
              "type": "fill"
            }
          ],
          "legendFormat": "failed nodes",
          "measurement": "kmm_health",
          "orderByTime": "ASC",
          "policy": "default",
          "rawQuery": true,
          "refId": "B",
          "resultFormat": "time_series",
          "select": [
            [
              {
                "params": [
                  "failed_nodes"
                ],
                "type": "field"
              }
            ]
          ]
        }
      ],
      "title": "Node Status",
      "type": "timeseries"
    },
    {
      "collapsed": false,
      "datasource": {
        "uid": "$datasource"
      },
      "gridPos": {
        "h": 1,
        "w": 24,
        "x": 0,
        "y": 10
      },
      "id": 20,
      "targets": [
        {
          "datasource": {
            "uid": "$datasource"
          },
          "refId": "A"
        }
      ],
      "title": "JVM overview",
      "type": "row"
    },
    {
      "datasource": {
        "uid": "$datasource"
      },
      "description": "Heap Memory Usage shows the amount of memory that is using for the heap.",
      "fieldConfig": {
        "defaults": {
          "color": {
            "mode": "palette-classic"
          },
          "custom": {
            "axisBorderShow": false,
            "axisCenteredZero": false,
            "axisColorMode": "text",
            "axisLabel": "",
            "axisPlacement": "auto",
            "barAlignment": 0,
            "barWidthFactor": 0.6,
            "drawStyle": "line",
            "fillOpacity": 10,
            "gradientMode": "none",
            "hideFrom": {
              "legend": false,
              "tooltip": false,
              "viz": false
            },
            "insertNulls": false,
            "lineInterpolation": "linear",
            "lineWidth": 1,
            "pointSize": 5,
            "scaleDistribution": {
              "type": "linear"
            },
            "showPoints": "never",
            "spanNulls": true,
            "stacking": {
              "group": "A",
              "mode": "none"
            },
            "thresholdsStyle": {
              "mode": "off"
            }
          },
          "mappings": [],
          "thresholds": {
            "mode": "absolute",
            "steps": [
              {
                "color": "green",
                "value": null
              },
              {
                "color": "red",
                "value": 80
              }
            ]
          },
          "unit": "decbytes"
        },
        "overrides": [
          {
            "matcher": {
              "id": "byName",
              "options": "Heap Memory - Max"
            },
            "properties": [
              {
                "id": "color",
                "value": {
                  "fixedColor": "#ef843c",
                  "mode": "fixed"
                }
              }
            ]
          },
          {
            "matcher": {
              "id": "byValue",
              "options": {
                "op": "gte",
                "reducer": "allIsNull",
                "value": 0
              }
            },
            "properties": [
              {
                "id": "custom.hideFrom",
                "value": {
                  "legend": true,
                  "tooltip": true,
                  "viz": false
                }
              }
            ]
          }
        ]
      },
      "gridPos": {
        "h": 9,
        "w": 12,
        "x": 0,
        "y": 11
      },
      "id": 22,
      "options": {
        "legend": {
          "calcs": [
            "mean",
            "lastNotNull",
            "max",
            "min"
          ],
          "displayMode": "table",
          "placement": "bottom",
          "showLegend": true
        },
        "tooltip": {
          "mode": "multi",
          "sort": "none"
        }
      },
      "targets": [
        {
          "alias": "$tag_url HeapMemoryUsage - Commited",
          "datasource": {
            "uid": "$datasource"
          },
          "expr": "max(java_Memory_HeapMemoryUsage_committed{project_name=~\"$project\",url=~\"$host\" ,cluster=\"$cluster\"}) by (url)",
          "groupBy": [
            {
              "params": [
                "$__interval"
              ],
              "type": "time"
            },
            {
              "params": [
                "url"
              ],
              "type": "tag"
            },
            {
              "params": [
                "none"
              ],
              "type": "fill"
            }
          ],
          "hide": false,
          "legendFormat": "committed {{url}}",
          "measurement": "jvm_memory",
          "orderByTime": "ASC",
          "policy": "default",
          "rawQuery": true,
          "refId": "D",
          "resultFormat": "time_series",
          "select": [
            [
              {
                "params": [
                  "HeapMemoryUsage.committed"
                ],
                "type": "field"
              }
            ]
          ],
          "tags": [
            {
              "key": "url",
              "operator": "=~",
              "value": "/^$host$/"
            }
          ]
        },
        {
          "alias": "$tag_url Heap Memory - Used",
          "datasource": {
            "uid": "$datasource"
          },
          "expr": "max(java_Memory_HeapMemoryUsage_used{project_name=~\"$project\",url=~\"$host\" ,cluster=\"$cluster\"}) by (url)",
          "groupBy": [
            {
              "params": [
                "$__interval"
              ],
              "type": "time"
            },
            {
              "params": [
                "none"
              ],
              "type": "fill"
            }
          ],
          "hide": false,
          "legendFormat": "used {{url}}",
          "measurement": "java_memory",
          "orderByTime": "ASC",
          "policy": "default",
          "rawQuery": true,
          "refId": "B",
          "resultFormat": "time_series",
          "select": [
            [
              {
                "params": [
                  "HeapMemoryUsage.used"
                ],
                "type": "field"
              }
            ]
          ],
          "tags": [
            {
              "key": "EC2_IPADDRESS",
              "operator": "=~",
              "value": "/^$IP$/"
            }
          ]
        },
        {
          "alias": "$tag_url Heap Memory - Max",
          "datasource": {
            "uid": "$datasource"
          },
          "expr": "max(java_Memory_HeapMemoryUsage_max{project_name=~\"$project\",url=~\"$host\" ,cluster=\"$cluster\"}) by (url)",
          "groupBy": [
            {
              "params": [
                "$__interval"
              ],
              "type": "time"
            },
            {
              "params": [
                "none"
              ],
              "type": "fill"
            }
          ],
          "hide": false,
          "legendFormat": "max {{url}}",
          "measurement": "java_memory",
          "orderByTime": "ASC",
          "policy": "default",
          "rawQuery": true,
          "refId": "C",
          "resultFormat": "time_series",
          "select": [
            [
              {
                "params": [
                  "HeapMemoryUsage.max"
                ],
                "type": "field"
              }
            ]
          ],
          "tags": [
            {
              "key": "EC2_IPADDRESS",
              "operator": "=~",
              "value": "/^$IP$/"
            }
          ]
        }
      ],
      "title": "Heap Memory Usage",
      "type": "timeseries"
    },
    {
      "datasource": {
        "uid": "$datasource"
      },
      "description": "Eden Space shows the amount of memory that is using for eden space. A metric value of \"-1\" means that the value is not set",
      "fieldConfig": {
        "defaults": {
          "color": {
            "mode": "palette-classic"
          },
          "custom": {
            "axisBorderShow": false,
            "axisCenteredZero": false,
            "axisColorMode": "text",
            "axisLabel": "",
            "axisPlacement": "auto",
            "barAlignment": 0,
            "barWidthFactor": 0.6,
            "drawStyle": "line",
            "fillOpacity": 10,
            "gradientMode": "none",
            "hideFrom": {
              "legend": false,
              "tooltip": false,
              "viz": false
            },
            "insertNulls": false,
            "lineInterpolation": "linear",
            "lineWidth": 1,
            "pointSize": 5,
            "scaleDistribution": {
              "type": "linear"
            },
            "showPoints": "never",
            "spanNulls": true,
            "stacking": {
              "group": "A",
              "mode": "none"
            },
            "thresholdsStyle": {
              "mode": "off"
            }
          },
          "mappings": [],
          "thresholds": {
            "mode": "absolute",
            "steps": [
              {
                "color": "green",
                "value": null
              },
              {
                "color": "red",
                "value": 80
              }
            ]
          },
          "unit": "bytes"
        },
        "overrides": []
      },
      "gridPos": {
        "h": 9,
        "w": 12,
        "x": 12,
        "y": 11
      },
      "id": 24,
      "options": {
        "legend": {
          "calcs": [
            "mean",
            "lastNotNull",
            "max",
            "min"
          ],
          "displayMode": "table",
          "placement": "bottom",
          "showLegend": true
        },
        "tooltip": {
          "mode": "multi",
          "sort": "none"
        }
      },
      "targets": [
        {
          "alias": "$tag_url - Initial",
          "datasource": {
            "uid": "$datasource"
          },
          "expr": "max(jvm_memory_pool_bytes_init{pool=\"G1 Eden Space\",project_name=~\"$project\",url=~\"$host\" ,cluster=\"$cluster\"}) by (url)",
          "groupBy": [
            {
              "params": [
                "$__interval"
              ],
              "type": "time"
            },
            {
              "params": [
                "url"
              ],
              "type": "tag"
            },
            {
              "params": [
                "null"
              ],
              "type": "fill"
            }
          ],
          "legendFormat": "init {{url}}",
          "measurement": "jvm_garbage_collector",
          "orderByTime": "ASC",
          "policy": "default",
          "rawQuery": true,
          "refId": "A",
          "resultFormat": "time_series",
          "select": [
            [
              {
                "params": [
                  "LastGcInfo.memoryUsageAfterGc.PS Eden Space.init"
                ],
                "type": "field"
              }
            ]
          ],
          "tags": [
            {
              "key": "project_name",
              "operator": "=~",
              "value": "/^$project$/"
            }
          ]
        },
        {
          "alias": "$tag_url - Committed",
          "datasource": {
            "uid": "$datasource"
          },
          "expr": "max(jvm_memory_pool_bytes_committed{pool=\"G1 Eden Space\",project_name=~\"$project\",url=~\"$host\" ,cluster=\"$cluster\"}) by (url)",
          "groupBy": [
            {
              "params": [
                "$__interval"
              ],
              "type": "time"
            },
            {
              "params": [
                "url"
              ],
              "type": "tag"
            },
            {
              "params": [
                "null"
              ],
              "type": "fill"
            }
          ],
          "legendFormat": "committed {{url}}",
          "measurement": "jvm_garbage_collector",
          "orderByTime": "ASC",
          "policy": "default",
          "rawQuery": true,
          "refId": "B",
          "resultFormat": "time_series",
          "select": [
            [
              {
                "params": [
                  "LastGcInfo.memoryUsageAfterGc.PS Eden Space.committed"
                ],
                "type": "field"
              }
            ]
          ],
          "tags": [
            {
              "key": "project_name",
              "operator": "=~",
              "value": "/^$project$/"
            }
          ]
        },
        {
          "alias": "$tag_url - Used",
          "datasource": {
            "uid": "$datasource"
          },
          "expr": "max(jvm_memory_pool_bytes_used{pool=\"G1 Eden Space\",project_name=~\"$project\",url=~\"$host\" ,cluster=\"$cluster\"}) by (url)",
          "groupBy": [
            {
              "params": [
                "$__interval"
              ],
              "type": "time"
            },
            {
              "params": [
                "null"
              ],
              "type": "fill"
            }
          ],
          "legendFormat": "used {{url}}",
          "orderByTime": "ASC",
          "policy": "default",
          "rawQuery": true,
          "refId": "C",
          "resultFormat": "time_series",
          "select": [
            [
              {
                "params": [
                  "value"
                ],
                "type": "field"
              }
            ]
          ],
          "tags": [
            {
              "key": "project_name",
              "operator": "=~",
              "value": "/^$project$/"
            }
          ]
        },
        {
          "alias": "$tag_url - Max",
          "datasource": {
            "uid": "$datasource"
          },
          "expr": "max(jvm_memory_pool_bytes_max{pool=\"G1 Eden Space\",project_name=~\"$project\",url=~\"$host\" ,cluster=\"$cluster\"}) by (url)",
          "groupBy": [
            {
              "params": [
                "$__interval"
              ],
              "type": "time"
            },
            {
              "params": [
                "null"
              ],
              "type": "fill"
            }
          ],
          "legendFormat": "max {{url}}",
          "orderByTime": "ASC",
          "policy": "default",
          "rawQuery": true,
          "refId": "D",
          "resultFormat": "time_series",
          "select": [
            [
              {
                "params": [
                  "value"
                ],
                "type": "field"
              }
            ]
          ],
          "tags": [
            {
              "key": "project_name",
              "operator": "=~",
              "value": "/^$project$/"
            }
          ]
        }
      ],
      "title": "Eden Space",
      "type": "timeseries"
    },
    {
      "datasource": {
        "uid": "$datasource"
      },
      "description": "Survivor Space shows the amount of memory that is using for survivor space. A metric value of \"-1\" means that the value is not set",
      "fieldConfig": {
        "defaults": {
          "color": {
            "mode": "palette-classic"
          },
          "custom": {
            "axisBorderShow": false,
            "axisCenteredZero": false,
            "axisColorMode": "text",
            "axisLabel": "",
            "axisPlacement": "auto",
            "barAlignment": 0,
            "barWidthFactor": 0.6,
            "drawStyle": "line",
            "fillOpacity": 10,
            "gradientMode": "none",
            "hideFrom": {
              "legend": false,
              "tooltip": false,
              "viz": false
            },
            "insertNulls": false,
            "lineInterpolation": "linear",
            "lineWidth": 1,
            "pointSize": 5,
            "scaleDistribution": {
              "type": "linear"
            },
            "showPoints": "never",
            "spanNulls": true,
            "stacking": {
              "group": "A",
              "mode": "none"
            },
            "thresholdsStyle": {
              "mode": "off"
            }
          },
          "mappings": [],
          "thresholds": {
            "mode": "absolute",
            "steps": [
              {
                "color": "green",
                "value": null
              },
              {
                "color": "red",
                "value": 80
              }
            ]
          },
          "unit": "decbytes"
        },
        "overrides": [
          {
            "matcher": {
              "id": "byValue",
              "options": {
                "op": "gte",
                "reducer": "allIsNull",
                "value": 0
              }
            },
            "properties": [
              {
                "id": "custom.hideFrom",
                "value": {
                  "legend": true,
                  "tooltip": true,
                  "viz": false
                }
              }
            ]
          }
        ]
      },
      "gridPos": {
        "h": 9,
        "w": 12,
        "x": 0,
        "y": 20
      },
      "id": 26,
      "options": {
        "legend": {
          "calcs": [
            "mean",
            "lastNotNull",
            "max",
            "min"
          ],
          "displayMode": "table",
          "placement": "bottom",
          "showLegend": true
        },
        "tooltip": {
          "mode": "multi",
          "sort": "none"
        }
      },
      "targets": [
        {
          "alias": "$tag_url - Init",
          "datasource": {
            "uid": "$datasource"
          },
          "expr": "max(jvm_memory_pool_bytes_committed{pool=\"G1 Survivor Space\",project_name=~\"$project\",url=~\"$host\" ,cluster=\"$cluster\"}) by (url)",
          "groupBy": [
            {
              "params": [
                "name"
              ],
              "type": "tag"
            }
          ],
          "hide": false,
          "legendFormat": "committed {{url}}",
          "measurement": "java_last_garbage_collection",
          "orderByTime": "ASC",
          "policy": "default",
          "rawQuery": true,
          "refId": "B",
          "resultFormat": "time_series",
          "select": [
            [
              {
                "params": [
                  "LastGcInfo.LastGcInfo.memoryUsageAfterGc.G1 Survivor Space.init"
                ],
                "type": "field"
              }
            ],
            [
              {
                "params": [
                  "LastGcInfo.LastGcInfo.memoryUsageAfterGc.PS Survivor Space.init"
                ],
                "type": "field"
              }
            ],
            [
              {
                "params": [
                  "LastGcInfo.LastGcInfo.memoryUsageAfterGc.Par Survivor Space.init"
                ],
                "type": "field"
              }
            ]
          ],
          "tags": [
            {
              "key": "EC2_IPADDRESS",
              "operator": "=~",
              "value": "/^$IP$/"
            },
            {
              "condition": "AND",
              "key": "name",
              "operator": "=",
              "value": "G1 Young Generation"
            },
            {
              "condition": "OR",
              "key": "name",
              "operator": "=",
              "value": "PS Scavenge"
            },
            {
              "condition": "OR",
              "key": "name",
              "operator": "=",
              "value": "ParNew"
            }
          ]
        },
        {
          "alias": "$tag_url - Commited",
          "datasource": {
            "uid": "$datasource"
          },
          "expr": "max(jvm_memory_pool_bytes_max{pool=\"G1 Survivor Space\",project_name=~\"$project\",url=~\"$host\" ,cluster=\"$cluster\"}) by (url)",
          "groupBy": [
            {
              "params": [
                "name"
              ],
              "type": "tag"
            }
          ],
          "hide": false,
          "legendFormat": "max {{url}}",
          "measurement": "java_last_garbage_collection",
          "orderByTime": "ASC",
          "policy": "default",
          "rawQuery": true,
          "refId": "A",
          "resultFormat": "time_series",
          "select": [
            [
              {
                "params": [
                  "LastGcInfo.LastGcInfo.memoryUsageAfterGc.G1 Survivor Space.committed"
                ],
                "type": "field"
              }
            ],
            [
              {
                "params": [
                  "LastGcInfo.LastGcInfo.memoryUsageAfterGc.PS Survivor Space.committed"
                ],
                "type": "field"
              }
            ],
            [
              {
                "params": [
                  "LastGcInfo.LastGcInfo.memoryUsageAfterGc.Par Survivor Space.committed"
                ],
                "type": "field"
              }
            ]
          ],
          "tags": [
            {
              "key": "EC2_IPADDRESS",
              "operator": "=~",
              "value": "/^$IP$/"
            },
            {
              "condition": "AND",
              "key": "name",
              "operator": "=",
              "value": "G1 Young Generation"
            },
            {
              "condition": "OR",
              "key": "name",
              "operator": "=",
              "value": "PS Scavenge"
            },
            {
              "condition": "OR",
              "key": "name",
              "operator": "=",
              "value": "ParNew"
            }
          ]
        },
        {
          "alias": "$tag_url - Used",
          "datasource": {
            "uid": "$datasource"
          },
          "expr": "max(jvm_memory_pool_bytes_used{pool=\"G1 Survivor Space\",project_name=~\"$project\",url=~\"$host\" ,cluster=\"$cluster\"}) by (url)",
          "groupBy": [
            {
              "params": [
                "name"
              ],
              "type": "tag"
            }
          ],
          "hide": false,
          "legendFormat": "used {{url}}",
          "measurement": "java_last_garbage_collection",
          "orderByTime": "ASC",
          "policy": "default",
          "rawQuery": true,
          "refId": "D",
          "resultFormat": "time_series",
          "select": [
            [
              {
                "params": [
                  "LastGcInfo.LastGcInfo.memoryUsageAfterGc.G1 Survivor Space.used"
                ],
                "type": "field"
              }
            ],
            [
              {
                "params": [
                  "LastGcInfo.LastGcInfo.memoryUsageAfterGc.PS Survivor Space.used"
                ],
                "type": "field"
              }
            ],
            [
              {
                "params": [
                  "LastGcInfo.LastGcInfo.memoryUsageBeforeGc.Par Survivor Space.used"
                ],
                "type": "field"
              }
            ]
          ],
          "tags": [
            {
              "key": "EC2_IPADDRESS",
              "operator": "=~",
              "value": "/^$IP$/"
            },
            {
              "condition": "AND",
              "key": "name",
              "operator": "=",
              "value": "G1 Young Generation"
            },
            {
              "condition": "OR",
              "key": "name",
              "operator": "=",
              "value": "PS Scavenge"
            },
            {
              "condition": "OR",
              "key": "name",
              "operator": "=",
              "value": "ParNew"
            }
          ]
        },
        {
          "alias": "$tag_url - Max",
          "datasource": {
            "uid": "$datasource"
          },
          "expr": "max(jvm_memory_pool_bytes_init{pool=\"G1 Survivor Space\",project_name=~\"$project\",url=~\"$host\" ,cluster=\"$cluster\"}) by (url)",
          "groupBy": [
            {
              "params": [
                "name"
              ],
              "type": "tag"
            }
          ],
          "hide": true,
          "legendFormat": "init {{url}}",
          "measurement": "java_last_garbage_collection",
          "orderByTime": "ASC",
          "policy": "default",
          "rawQuery": true,
          "refId": "C",
          "resultFormat": "time_series",
          "select": [
            [
              {
                "params": [
                  "LastGcInfo.LastGcInfo.memoryUsageAfterGc.G1 Survivor Space.max"
                ],
                "type": "field"
              }
            ],
            [
              {
                "params": [
                  "LastGcInfo.LastGcInfo.memoryUsageAfterGc.PS Survivor Space.max"
                ],
                "type": "field"
              }
            ],
            [
              {
                "params": [
                  "LastGcInfo.LastGcInfo.memoryUsageAfterGc.Par Survivor Space.max"
                ],
                "type": "field"
              }
            ]
          ],
          "tags": [
            {
              "key": "EC2_IPADDRESS",
              "operator": "=~",
              "value": "/^$IP$/"
            },
            {
              "condition": "AND",
              "key": "name",
              "operator": "=",
              "value": "G1 Young Generation"
            },
            {
              "condition": "OR",
              "key": "name",
              "operator": "=",
              "value": "PS Scavenge"
            },
            {
              "condition": "OR",
              "key": "name",
              "operator": "=",
              "value": "ParNew"
            }
          ]
        }
      ],
      "title": "Survivor Space",
      "type": "timeseries"
    },
    {
      "datasource": {
        "uid": "$datasource"
      },
      "description": "Non-Heap Memory Usage shows the amount of memory that is using for non-heap area.",
      "fieldConfig": {
        "defaults": {
          "color": {
            "mode": "palette-classic"
          },
          "custom": {
            "axisBorderShow": false,
            "axisCenteredZero": false,
            "axisColorMode": "text",
            "axisLabel": "",
            "axisPlacement": "auto",
            "barAlignment": 0,
            "barWidthFactor": 0.6,
            "drawStyle": "line",
            "fillOpacity": 10,
            "gradientMode": "none",
            "hideFrom": {
              "legend": false,
              "tooltip": false,
              "viz": false
            },
            "insertNulls": false,
            "lineInterpolation": "linear",
            "lineWidth": 1,
            "pointSize": 5,
            "scaleDistribution": {
              "type": "linear"
            },
            "showPoints": "never",
            "spanNulls": true,
            "stacking": {
              "group": "A",
              "mode": "none"
            },
            "thresholdsStyle": {
              "mode": "off"
            }
          },
          "mappings": [],
          "thresholds": {
            "mode": "absolute",
            "steps": [
              {
                "color": "green",
                "value": null
              },
              {
                "color": "red",
                "value": 80
              }
            ]
          },
          "unit": "decbytes"
        },
        "overrides": [
          {
            "matcher": {
              "id": "byName",
              "options": "Heap Memory - Max"
            },
            "properties": [
              {
                "id": "color",
                "value": {
                  "fixedColor": "#ef843c",
                  "mode": "fixed"
                }
              }
            ]
          },
          {
            "matcher": {
              "id": "byValue",
              "options": {
                "op": "gte",
                "reducer": "allIsNull",
                "value": 0
              }
            },
            "properties": [
              {
                "id": "custom.hideFrom",
                "value": {
                  "legend": true,
                  "tooltip": true,
                  "viz": false
                }
              }
            ]
          }
        ]
      },
      "gridPos": {
        "h": 9,
        "w": 12,
        "x": 12,
        "y": 20
      },
      "id": 28,
      "options": {
        "legend": {
          "calcs": [
            "mean",
            "lastNotNull",
            "max",
            "min"
          ],
          "displayMode": "table",
          "placement": "bottom",
          "showLegend": true
        },
        "tooltip": {
          "mode": "multi",
          "sort": "none"
        }
      },
      "targets": [
        {
          "alias": "$tag_url Non-Heap Memory - Init",
          "datasource": {
            "uid": "$datasource"
          },
          "expr": "max(java_Memory_NonHeapMemoryUsage_init{project_name=~\"$project\",url=~\"$host\" ,cluster=\"$cluster\"}) by (url)",
          "groupBy": [
            {
              "params": [
                "$__interval"
              ],
              "type": "time"
            },
            {
              "params": [
                "none"
              ],
              "type": "fill"
            }
          ],
          "hide": true,
          "legendFormat": "init {{url}}",
          "measurement": "java_memory",
          "orderByTime": "ASC",
          "policy": "default",
          "rawQuery": true,
          "refId": "A",
          "resultFormat": "time_series",
          "select": [
            [
              {
                "params": [
                  "NonHeapMemoryUsage.init"
                ],
                "type": "field"
              }
            ]
          ],
          "tags": [
            {
              "key": "EC2_IPADDRESS",
              "operator": "=~",
              "value": "/^$IP$/"
            }
          ]
        },
        {
          "alias": "$tag_url NonHeapMemoryUsage - Commited",
          "datasource": {
            "uid": "$datasource"
          },
          "expr": "max(java_Memory_NonHeapMemoryUsage_committed{project_name=~\"$project\",url=~\"$host\" ,cluster=\"$cluster\"}) by (url)",
          "groupBy": [
            {
              "params": [
                "$__interval"
              ],
              "type": "time"
            },
            {
              "params": [
                "none"
              ],
              "type": "fill"
            }
          ],
          "legendFormat": "committed {{url}}",
          "measurement": "java_memory",
          "orderByTime": "ASC",
          "policy": "default",
          "rawQuery": true,
          "refId": "D",
          "resultFormat": "time_series",
          "select": [
            [
              {
                "params": [
                  "NonHeapMemoryUsage.committed"
                ],
                "type": "field"
              }
            ]
          ],
          "tags": [
            {
              "key": "EC2_IPADDRESS",
              "operator": "=~",
              "value": "/^$IP$/"
            }
          ]
        },
        {
          "alias": "$tag_url Non-Heap Memory - Used",
          "datasource": {
            "uid": "$datasource"
          },
          "expr": "max(java_Memory_NonHeapMemoryUsage_used{project_name=~\"$project\",url=~\"$host\" ,cluster=\"$cluster\"}) by (url)",
          "groupBy": [
            {
              "params": [
                "$__interval"
              ],
              "type": "time"
            },
            {
              "params": [
                "none"
              ],
              "type": "fill"
            }
          ],
          "legendFormat": "used {{url}}",
          "measurement": "java_memory",
          "orderByTime": "ASC",
          "policy": "default",
          "rawQuery": true,
          "refId": "B",
          "resultFormat": "time_series",
          "select": [
            [
              {
                "params": [
                  "NonHeapMemoryUsage.used"
                ],
                "type": "field"
              }
            ]
          ],
          "tags": [
            {
              "key": "EC2_IPADDRESS",
              "operator": "=~",
              "value": "/^$IP$/"
            }
          ]
        },
        {
          "alias": "$tag_url Non-Heap Memory - Max",
          "datasource": {
            "uid": "$datasource"
          },
          "expr": "max(java_Memory_NonHeapMemoryUsage_max{project_name=~\"$project\",url=~\"$host\" ,cluster=\"$cluster\"}) by (url)",
          "groupBy": [
            {
              "params": [
                "$__interval"
              ],
              "type": "time"
            },
            {
              "params": [
                "none"
              ],
              "type": "fill"
            }
          ],
          "hide": true,
          "legendFormat": "max {{url}}",
          "measurement": "java_memory",
          "orderByTime": "ASC",
          "policy": "default",
          "rawQuery": true,
          "refId": "C",
          "resultFormat": "time_series",
          "select": [
            [
              {
                "params": [
                  "NonHeapMemoryUsage.max"
                ],
                "type": "field"
              }
            ]
          ],
          "tags": [
            {
              "key": "EC2_IPADDRESS",
              "operator": "=~",
              "value": "/^$IP$/"
            }
          ]
        }
      ],
      "title": "Non-Heap Memory Usage",
      "type": "timeseries"
    },
    {
      "datasource": {
        "uid": "$datasource"
      },
      "description": "Metaspace shows the amount of memory that is using for metaspace.",
      "fieldConfig": {
        "defaults": {
          "color": {
            "mode": "palette-classic"
          },
          "custom": {
            "axisBorderShow": false,
            "axisCenteredZero": false,
            "axisColorMode": "text",
            "axisLabel": "",
            "axisPlacement": "auto",
            "barAlignment": 0,
            "barWidthFactor": 0.6,
            "drawStyle": "line",
            "fillOpacity": 10,
            "gradientMode": "none",
            "hideFrom": {
              "legend": false,
              "tooltip": false,
              "viz": false
            },
            "insertNulls": false,
            "lineInterpolation": "linear",
            "lineWidth": 1,
            "pointSize": 5,
            "scaleDistribution": {
              "type": "linear"
            },
            "showPoints": "never",
            "spanNulls": true,
            "stacking": {
              "group": "A",
              "mode": "none"
            },
            "thresholdsStyle": {
              "mode": "off"
            }
          },
          "mappings": [],
          "thresholds": {
            "mode": "absolute",
            "steps": [
              {
                "color": "green",
                "value": null
              },
              {
                "color": "red",
                "value": 80
              }
            ]
          },
          "unit": "decbytes"
        },
        "overrides": [
          {
            "matcher": {
              "id": "byValue",
              "options": {
                "op": "gte",
                "reducer": "allIsNull",
                "value": 0
              }
            },
            "properties": [
              {
                "id": "custom.hideFrom",
                "value": {
                  "legend": true,
                  "tooltip": true,
                  "viz": false
                }
              }
            ]
          }
        ]
      },
      "gridPos": {
        "h": 9,
        "w": 12,
        "x": 0,
        "y": 29
      },
      "id": 30,
      "options": {
        "legend": {
          "calcs": [
            "mean",
            "lastNotNull",
            "max",
            "min"
          ],
          "displayMode": "table",
          "placement": "bottom",
          "showLegend": true
        },
        "tooltip": {
          "mode": "multi",
          "sort": "none"
        }
      },
      "targets": [
        {
          "alias": "$tag_url - Init",
          "datasource": {
            "uid": "$datasource"
          },
          "expr": "max(jvm_memory_pool_bytes_init{pool=\"Metaspace\",project_name=~\"$project\",url=~\"$host\" ,cluster=\"$cluster\"}) by (url)",
          "groupBy": [
            {
              "params": [
                "name"
              ],
              "type": "tag"
            }
          ],
          "hide": true,
          "legendFormat": "init {{url}}",
          "measurement": "java_last_garbage_collection",
          "orderByTime": "ASC",
          "policy": "default",
          "rawQuery": true,
          "refId": "B",
          "resultFormat": "time_series",
          "select": [
            [
              {
                "params": [
                  "LastGcInfo.LastGcInfo.memoryUsageAfterGc.Metaspace.init"
                ],
                "type": "field"
              }
            ]
          ],
          "tags": [
            {
              "key": "EC2_IPADDRESS",
              "operator": "=~",
              "value": "/^$IP$/"
            }
          ]
        },
        {
          "alias": "$tag_url - Commited",
          "datasource": {
            "uid": "$datasource"
          },
          "expr": "max(jvm_memory_pool_bytes_committed{pool=\"Metaspace\",project_name=~\"$project\",url=~\"$host\" ,cluster=\"$cluster\"}) by (url)",
          "groupBy": [
            {
              "params": [
                "name"
              ],
              "type": "tag"
            }
          ],
          "legendFormat": "committed {{url}}",
          "measurement": "java_last_garbage_collection",
          "orderByTime": "ASC",
          "policy": "default",
          "rawQuery": true,
          "refId": "E",
          "resultFormat": "time_series",
          "select": [
            [
              {
                "params": [
                  "LastGcInfo.LastGcInfo.memoryUsageAfterGc.Metaspace.committed"
                ],
                "type": "field"
              }
            ]
          ],
          "tags": [
            {
              "key": "EC2_IPADDRESS",
              "operator": "=~",
              "value": "/^$IP$/"
            }
          ]
        },
        {
          "alias": "$tag_url - Used",
          "datasource": {
            "uid": "$datasource"
          },
          "expr": "max(jvm_memory_pool_bytes_used{pool=\"Metaspace\",project_name=~\"$project\",url=~\"$host\" ,cluster=\"$cluster\"}) by (url)",
          "groupBy": [
            {
              "params": [
                "name"
              ],
              "type": "tag"
            }
          ],
          "hide": false,
          "legendFormat": "used {{url}}",
          "measurement": "java_last_garbage_collection",
          "orderByTime": "ASC",
          "policy": "default",
          "rawQuery": true,
          "refId": "D",
          "resultFormat": "time_series",
          "select": [
            [
              {
                "params": [
                  "LastGcInfo.LastGcInfo.memoryUsageAfterGc.Metaspace.used"
                ],
                "type": "field"
              }
            ]
          ],
          "tags": [
            {
              "key": "EC2_IPADDRESS",
              "operator": "=~",
              "value": "/^$IP$/"
            }
          ]
        },
        {
          "alias": "$tag_url - Max",
          "datasource": {
            "uid": "$datasource"
          },
          "expr": "max(jvm_memory_pool_bytes_max{pool=\"Metaspace\",project_name=~\"$project\",url=~\"$host\" ,cluster=\"$cluster\"}) by (url)",
          "groupBy": [
            {
              "params": [
                "name"
              ],
              "type": "tag"
            }
          ],
          "hide": true,
          "legendFormat": "max {{url}}",
          "measurement": "java_last_garbage_collection",
          "orderByTime": "ASC",
          "policy": "default",
          "rawQuery": true,
          "refId": "C",
          "resultFormat": "time_series",
          "select": [
            [
              {
                "params": [
                  "LastGcInfo.LastGcInfo.memoryUsageAfterGc.Metaspace.max"
                ],
                "type": "field"
              }
            ]
          ],
          "tags": [
            {
              "key": "EC2_IPADDRESS",
              "operator": "=~",
              "value": "/^$IP$/"
            }
          ]
        }
      ],
      "title": "Metaspace",
      "type": "timeseries"
    },
    {
      "datasource": {
        "uid": "$datasource"
      },
      "description": "Thread Count shows the amount of active threads.",
      "fieldConfig": {
        "defaults": {
          "color": {
            "mode": "palette-classic"
          },
          "custom": {
            "axisBorderShow": false,
            "axisCenteredZero": false,
            "axisColorMode": "text",
            "axisLabel": "",
            "axisPlacement": "auto",
            "barAlignment": 0,
            "barWidthFactor": 0.6,
            "drawStyle": "line",
            "fillOpacity": 10,
            "gradientMode": "none",
            "hideFrom": {
              "legend": false,
              "tooltip": false,
              "viz": false
            },
            "insertNulls": false,
            "lineInterpolation": "linear",
            "lineWidth": 1,
            "pointSize": 5,
            "scaleDistribution": {
              "type": "linear"
            },
            "showPoints": "never",
            "spanNulls": true,
            "stacking": {
              "group": "A",
              "mode": "none"
            },
            "thresholdsStyle": {
              "mode": "off"
            }
          },
          "mappings": [],
          "thresholds": {
            "mode": "absolute",
            "steps": [
              {
                "color": "green",
                "value": null
              },
              {
                "color": "red",
                "value": 80
              }
            ]
          },
          "unit": "short"
        },
        "overrides": [
          {
            "matcher": {
              "id": "byValue",
              "options": {
                "op": "gte",
                "reducer": "allIsNull",
                "value": 0
              }
            },
            "properties": [
              {
                "id": "custom.hideFrom",
                "value": {
                  "legend": true,
                  "tooltip": true,
                  "viz": false
                }
              }
            ]
          }
        ]
      },
      "gridPos": {
        "h": 9,
        "w": 12,
        "x": 12,
        "y": 29
      },
      "id": 32,
      "options": {
        "legend": {
          "calcs": [
            "mean",
            "lastNotNull",
            "max",
            "min"
          ],
          "displayMode": "table",
          "placement": "bottom",
          "showLegend": true
        },
        "tooltip": {
          "mode": "multi",
          "sort": "none"
        }
      },
      "targets": [
        {
          "alias": "$tag_url Total Started Thread Count",
          "datasource": {
            "uid": "$datasource"
          },
          "expr": "avg(java_Threading_TotalStartedThreadCount{project_name=~\"$project\",url=~\"$host\" ,cluster=\"$cluster\"}) by (url)",
          "groupBy": [
            {
              "params": [
                "$__interval"
              ],
              "type": "time"
            },
            {
              "params": [
                "none"
              ],
              "type": "fill"
            }
          ],
          "hide": false,
          "legendFormat": "started threads count: {{url}} ",
          "measurement": "java_threading",
          "orderByTime": "ASC",
          "policy": "default",
          "rawQuery": true,
          "refId": "D",
          "resultFormat": "time_series",
          "select": [
            [
              {
                "params": [
                  "TotalStartedThreadCount"
                ],
                "type": "field"
              }
            ]
          ],
          "tags": [
            {
              "key": "EC2_IPADDRESS",
              "operator": "=~",
              "value": "/^$IP$/"
            }
          ]
        },
        {
          "alias": "$tag_url Daemon Thread Count",
          "datasource": {
            "uid": "$datasource"
          },
          "expr": "avg(java_Threading_DaemonThreadCount{project_name=~\"$project\",url=~\"$host\" ,cluster=\"$cluster\"}) by (url)",
          "groupBy": [
            {
              "params": [
                "$__interval"
              ],
              "type": "time"
            },
            {
              "params": [
                "none"
              ],
              "type": "fill"
            }
          ],
          "hide": false,
          "legendFormat": "daemon threads count: {{url}}",
          "measurement": "java_threading",
          "orderByTime": "ASC",
          "policy": "default",
          "rawQuery": true,
          "refId": "A",
          "resultFormat": "time_series",
          "select": [
            [
              {
                "params": [
                  "DaemonThreadCount"
                ],
                "type": "field"
              }
            ]
          ],
          "tags": [
            {
              "key": "EC2_IPADDRESS",
              "operator": "=~",
              "value": "/^$IP$/"
            }
          ]
        },
        {
          "alias": "$tag_url Peak Thread Count",
          "datasource": {
            "uid": "$datasource"
          },
          "expr": "avg(java_Threading_PeakThreadCount{project_name=~\"$project\",url=~\"$host\" ,cluster=\"$cluster\"}) by (url)",
          "groupBy": [
            {
              "params": [
                "$__interval"
              ],
              "type": "time"
            },
            {
              "params": [
                "none"
              ],
              "type": "fill"
            }
          ],
          "hide": false,
          "legendFormat": "peak threads count: {{url}}",
          "measurement": "java_threading",
          "orderByTime": "ASC",
          "policy": "default",
          "rawQuery": true,
          "refId": "B",
          "resultFormat": "time_series",
          "select": [
            [
              {
                "params": [
                  "PeakThreadCount"
                ],
                "type": "field"
              }
            ]
          ],
          "tags": [
            {
              "key": "EC2_IPADDRESS",
              "operator": "=~",
              "value": "/^$IP$/"
            }
          ]
        },
        {
          "alias": "$tag_url Thread Count",
          "datasource": {
            "uid": "$datasource"
          },
          "expr": "avg(java_Threading_ThreadCount{project_name=~\"$project\",url=~\"$host\" ,cluster=\"$cluster\"}) by (url)",
          "groupBy": [
            {
              "params": [
                "$__interval"
              ],
              "type": "time"
            },
            {
              "params": [
                "none"
              ],
              "type": "fill"
            }
          ],
          "hide": false,
          "legendFormat": "threads count: {{url}}",
          "measurement": "java_threading",
          "orderByTime": "ASC",
          "policy": "default",
          "rawQuery": true,
          "refId": "C",
          "resultFormat": "time_series",
          "select": [
            [
              {
                "params": [
                  "ThreadCount"
                ],
                "type": "field"
              }
            ]
          ],
          "tags": [
            {
              "key": "EC2_IPADDRESS",
              "operator": "=~",
              "value": "/^$IP$/"
            }
          ]
        }
      ],
      "title": "Thread Count",
      "type": "timeseries"
    },
    {
      "collapsed": false,
      "datasource": {
        "uid": "$datasource"
      },
      "gridPos": {
        "h": 1,
        "w": 24,
        "x": 0,
        "y": 38
      },
      "id": 16,
      "targets": [
        {
          "datasource": {
            "uid": "$datasource"
          },
          "refId": "A"
        }
      ],
      "title": "Replication status",
      "type": "row"
    },
    {
      "datasource": {
        "uid": "$datasource"
      },
      "description": "Replicated bytes shows the amount of replicated bytes.",
      "fieldConfig": {
        "defaults": {
          "mappings": [
            {
              "options": {
                "match": "null",
                "result": {
                  "text": "N/A"
                }
              },
              "type": "special"
            }
          ],
          "thresholds": {
            "mode": "absolute",
            "steps": [
              {
                "color": "green",
                "value": null
              },
              {
                "color": "red",
                "value": 80
              }
            ]
          },
          "unit": "bytes"
        },
        "overrides": []
      },
      "gridPos": {
        "h": 8,
        "w": 4,
        "x": 0,
        "y": 39
      },
      "id": 34,
      "maxDataPoints": 100,
      "options": {
        "colorMode": "value",
        "graphMode": "none",
        "justifyMode": "auto",
        "orientation": "horizontal",
        "percentChangeColorMode": "standard",
        "reduceOptions": {
          "calcs": [
            "lastNotNull"
          ],
          "fields": "",
          "values": false
        },
        "showPercentChange": false,
        "textMode": "auto",
        "wideLayout": true
      },
      "pluginVersion": "11.2.1",
      "targets": [
        {
          "alias": "bytes",
          "datasource": {
            "uid": "$datasource"
          },
          "expr": "sum(bytes_byte_count{target=~\"$target*\",project_name=~\"$project\" ,cluster=\"$cluster\"})",
          "instant": true,
          "measurement": "bytes",
          "orderByTime": "ASC",
          "policy": "default",
          "rawQuery": true,
          "refId": "A",
          "resultFormat": "time_series",
          "select": [
            [
              {
                "params": [
                  "byte-count"
                ],
                "type": "field"
              }
            ]
          ],
          "tags": [
            {
              "key": "target",
              "operator": "=~",
              "value": "/^$target$/"
            },
            {
              "condition": "AND",
              "key": "project_name",
              "operator": "=~",
              "value": "/^$project$/"
            }
          ]
        }
      ],
      "title": "Replicated bytes",
      "type": "stat"
    },
    {
      "datasource": {
        "uid": "$datasource"
      },
      "description": "Replicated records shows the amount of replicated bytes.",
      "fieldConfig": {
        "defaults": {
          "mappings": [
            {
              "options": {
                "match": "null",
                "result": {
                  "text": "N/A"
                }
              },
              "type": "special"
            }
          ],
          "thresholds": {
            "mode": "absolute",
            "steps": [
              {
                "color": "green",
                "value": null
              },
              {
                "color": "red",
                "value": 80
              }
            ]
          },
          "unit": "short"
        },
        "overrides": []
      },
      "gridPos": {
        "h": 8,
        "w": 4,
        "x": 4,
        "y": 39
      },
      "id": 36,
      "maxDataPoints": 100,
      "options": {
        "colorMode": "value",
        "graphMode": "none",
        "justifyMode": "auto",
        "orientation": "horizontal",
        "percentChangeColorMode": "standard",
        "reduceOptions": {
          "calcs": [
            "lastNotNull"
          ],
          "fields": "",
          "values": false
        },
        "showPercentChange": false,
        "textMode": "auto",
        "wideLayout": true
      },
      "pluginVersion": "11.2.1",
      "targets": [
        {
          "datasource": {
            "uid": "$datasource"
          },
          "expr": "sum(record_age_record_count{project_name=~\"$project\" ,cluster=\"$cluster\"})",
          "groupBy": [
            {
              "params": [
                "$__interval"
              ],
              "type": "time"
            },
            {
              "params": [
                "null"
              ],
              "type": "fill"
            }
          ],
          "measurement": "record-age",
          "orderByTime": "ASC",
          "policy": "default",
          "rawQuery": true,
          "refId": "A",
          "resultFormat": "time_series",
          "select": [
            [
              {
                "params": [
                  "record-count"
                ],
                "type": "field"
              }
            ]
          ],
          "tags": [
            {
              "key": "project_name",
              "operator": "=~",
              "value": "/^$project$/"
            }
          ]
        }
      ],
      "title": "Replicated records",
      "type": "stat"
    },
    {
      "datasource": {
        "uid": "$datasource"
      },
      "description": "Record age shows age of each record when consumed.",
      "fieldConfig": {
        "defaults": {
          "color": {
            "mode": "palette-classic"
          },
          "custom": {
            "axisBorderShow": false,
            "axisCenteredZero": false,
            "axisColorMode": "text",
            "axisLabel": "",
            "axisPlacement": "auto",
            "barAlignment": 0,
            "barWidthFactor": 0.6,
            "drawStyle": "line",
            "fillOpacity": 10,
            "gradientMode": "none",
            "hideFrom": {
              "legend": false,
              "tooltip": false,
              "viz": false
            },
            "insertNulls": false,
            "lineInterpolation": "linear",
            "lineWidth": 1,
            "pointSize": 5,
            "scaleDistribution": {
              "type": "linear"
            },
            "showPoints": "never",
            "spanNulls": true,
            "stacking": {
              "group": "A",
              "mode": "none"
            },
            "thresholdsStyle": {
              "mode": "off"
            }
          },
          "mappings": [],
          "thresholds": {
            "mode": "absolute",
            "steps": [
              {
                "color": "green",
                "value": null
              },
              {
                "color": "red",
                "value": 80
              }
            ]
          },
          "unit": "ms"
        },
        "overrides": []
      },
      "gridPos": {
        "h": 8,
        "w": 16,
        "x": 8,
        "y": 39
      },
      "id": 8,
      "options": {
        "legend": {
          "calcs": [
            "mean",
            "lastNotNull",
            "max",
            "min"
          ],
          "displayMode": "table",
          "placement": "bottom",
          "showLegend": true
        },
        "tooltip": {
          "mode": "multi",
          "sort": "none"
        }
      },
      "targets": [
        {
          "alias": "record-age",
          "datasource": {
            "uid": "$datasource"
          },
          "expr": "avg(record_age_record_age_ms{target=~\"$target*\",project_name=~\"$project\",topic=~\"$topic\" ,cluster=\"$cluster\"}) by (target,topic)",
          "groupBy": [
            {
              "params": [
                "$__interval"
              ],
              "type": "time"
            },
            {
              "params": [
                "null"
              ],
              "type": "fill"
            }
          ],
          "measurement": "record-age",
          "orderByTime": "ASC",
          "policy": "default",
          "refId": "A",
          "resultFormat": "time_series",
          "select": [
            [
              {
                "params": [
                  "record-age-ms"
                ],
                "type": "field"
              }
            ]
          ],
          "tags": [
            {
              "key": "topic",
              "operator": "=~",
              "value": "/^$topic$/"
            },
            {
              "condition": "AND",
              "key": "target",
              "operator": "=~",
              "value": "/^$target$/"
            },
            {
              "condition": "AND",
              "key": "project_name",
              "operator": "=~",
              "value": "/^$project$/"
            }
          ]
        }
      ],
      "title": "Record age",
      "type": "timeseries"
    },
    {
      "datasource": {
        "uid": "$datasource"
      },
      "description": "Replication speed per second shows the amount of replicated bytes per second.",
      "fieldConfig": {
        "defaults": {
          "color": {
            "mode": "palette-classic"
          },
          "custom": {
            "axisBorderShow": false,
            "axisCenteredZero": false,
            "axisColorMode": "text",
            "axisLabel": "",
            "axisPlacement": "auto",
            "barAlignment": 0,
            "barWidthFactor": 0.6,
            "drawStyle": "line",
            "fillOpacity": 10,
            "gradientMode": "none",
            "hideFrom": {
              "legend": false,
              "tooltip": false,
              "viz": false
            },
            "insertNulls": false,
            "lineInterpolation": "linear",
            "lineWidth": 1,
            "pointSize": 5,
            "scaleDistribution": {
              "type": "linear"
            },
            "showPoints": "never",
            "spanNulls": true,
            "stacking": {
              "group": "A",
              "mode": "none"
            },
            "thresholdsStyle": {
              "mode": "off"
            }
          },
          "mappings": [],
          "thresholds": {
            "mode": "absolute",
            "steps": [
              {
                "color": "green",
                "value": null
              },
              {
                "color": "red",
                "value": 80
              }
            ]
          },
          "unit": "Bps"
        },
        "overrides": []
      },
      "gridPos": {
        "h": 8,
        "w": 24,
        "x": 0,
        "y": 47
      },
      "id": 37,
      "options": {
        "legend": {
          "calcs": [
            "mean",
            "lastNotNull",
            "max",
            "min"
          ],
          "displayMode": "table",
          "placement": "bottom",
          "showLegend": true
        },
        "tooltip": {
          "mode": "multi",
          "sort": "none"
        }
      },
      "targets": [
        {
          "alias": "replication-speed",
          "datasource": {
            "uid": "$datasource"
          },
          "expr": "avg(bytes_byte_rate{target=~\"$target*\",project_name=~\"$project\",topic=~\"$topic\" ,cluster=\"$cluster\"}) by (target,topic)",
          "groupBy": [
            {
              "params": [
                "$__interval"
              ],
              "type": "time"
            },
            {
              "params": [
                "null"
              ],
              "type": "fill"
            }
          ],
          "measurement": "bytes",
          "orderByTime": "ASC",
          "policy": "default",
          "rawQuery": true,
          "refId": "A",
          "resultFormat": "time_series",
          "select": [
            [
              {
                "params": [
                  "byte-rate"
                ],
                "type": "field"
              }
            ]
          ],
          "tags": [
            {
              "key": "project_name",
              "operator": "=~",
              "value": "/^$project$/"
            },
            {
              "condition": "AND",
              "key": "target",
              "operator": "=~",
              "value": "/^$target$/"
            },
            {
              "condition": "AND",
              "key": "topic",
              "operator": "=~",
              "value": "/^$topic$/"
            }
          ]
        }
      ],
      "title": "Replication speed per second",
      "type": "timeseries"
    },
    {
      "datasource": {
        "uid": "$datasource"
      },
      "description": "Replication latency shows a timespan between each record's timestamp and downstream ACK.",
      "fieldConfig": {
        "defaults": {
          "color": {
            "mode": "palette-classic"
          },
          "custom": {
            "axisBorderShow": false,
            "axisCenteredZero": false,
            "axisColorMode": "text",
            "axisLabel": "",
            "axisPlacement": "auto",
            "barAlignment": 0,
            "barWidthFactor": 0.6,
            "drawStyle": "line",
            "fillOpacity": 10,
            "gradientMode": "none",
            "hideFrom": {
              "legend": false,
              "tooltip": false,
              "viz": false
            },
            "insertNulls": false,
            "lineInterpolation": "linear",
            "lineWidth": 1,
            "pointSize": 5,
            "scaleDistribution": {
              "type": "linear"
            },
            "showPoints": "never",
            "spanNulls": true,
            "stacking": {
              "group": "A",
              "mode": "none"
            },
            "thresholdsStyle": {
              "mode": "off"
            }
          },
          "mappings": [],
          "thresholds": {
            "mode": "absolute",
            "steps": [
              {
                "color": "green",
                "value": null
              },
              {
                "color": "red",
                "value": 80
              }
            ]
          },
          "unit": "ms"
        },
        "overrides": []
      },
      "gridPos": {
        "h": 8,
        "w": 24,
        "x": 0,
        "y": 55
      },
      "id": 6,
      "options": {
        "legend": {
          "calcs": [
            "mean",
            "lastNotNull",
            "max",
            "min"
          ],
          "displayMode": "table",
          "placement": "bottom",
          "showLegend": true
        },
        "tooltip": {
          "mode": "multi",
          "sort": "none"
        }
      },
      "targets": [
        {
          "alias": "replication-latency",
          "datasource": {
            "uid": "$datasource"
          },
          "expr": "avg(replication_latency_replication_latency_ms{target=~\"$target*\",project_name=~\"$project\",topic=~\"$topic\" ,cluster=\"$cluster\"}) by (target,topic)",
          "groupBy": [
            {
              "params": [
                "$__interval"
              ],
              "type": "time"
            },
            {
              "params": [
                "null"
              ],
              "type": "fill"
            }
          ],
          "hide": false,
          "measurement": "replication-latency",
          "orderByTime": "ASC",
          "policy": "default",
          "rawQuery": true,
          "refId": "A",
          "resultFormat": "time_series",
          "select": [
            [
              {
                "params": [
                  "replication-latency-ms"
                ],
                "type": "field"
              }
            ]
          ],
          "tags": [
            {
              "key": "target",
              "operator": "=~",
              "value": "/^$target$/"
            },
            {
              "condition": "AND",
              "key": "topic",
              "operator": "=~",
              "value": "/^$topic$/"
            },
            {
              "condition": "AND",
              "key": "project_name",
              "operator": "=~",
              "value": "/^$project$/"
            }
          ]
        }
      ],
      "title": "Replication latency",
      "type": "timeseries"
    }
  ],
  "refresh": "10s",
  "schemaVersion": 39,
  "tags": [
    "Kafka Mirror Maker",
    "Prometheus"
  ],
  "templating": {
    "list": [
      {
        "current": {
          "selected": false,
          "text": "Platform Monitoring Prometheus",
          "value": "PC3E95692D54ABCC0"
        },
        "hide": 0,
        "includeAll": false,
        "label": "Cloud",
        "multi": false,
        "name": "datasource",
        "options": [],
        "query": "prometheus",
        "refresh": 1,
        "regex": "",
        "skipUrlSync": false,
        "type": "datasource"
      },
      {
        "current": {
          "isNone": true,
          "selected": false,
          "text": "None",
          "value": ""
        },
        "datasource": {
          "type": "prometheus",
          "uid": "$datasource"
        },
        "definition": "",
        "hide": 0,
        "includeAll": false,
        "label": "Cluster",
        "multi": false,
        "name": "cluster",
        "options": [],
        "query": {
          "query": "label_values(kmm_health_status_code, cluster)",
          "refId": "StandardVariableQuery"
        },
        "refresh": 1,
        "regex": "",
        "skipUrlSync": false,
        "sort": 0,
        "type": "query"
      },
      {
        "current": {
          "isNone": true,
          "selected": true,
          "text": "None",
          "value": ""
        },
        "datasource": {
          "type": "prometheus",
          "uid": "$datasource"
        },
        "definition": "label_values(namespace)",
        "hide": 0,
        "includeAll": false,
        "label": "Project",
        "multi": false,
        "name": "project",
        "options": [],
        "query": "label_values(kmm_health_status_code{cluster=\"$cluster\"}, namespace)",
        "refresh": 1,
        "regex": "",
        "skipUrlSync": false,
        "sort": 0,
        "type": "query",
        "useTags": false
      },
      {
        "allValue": ".",
        "current": {
          "selected": false,
          "text": "All",
          "value": "$__all"
        },
        "datasource": {
          "type": "prometheus",
          "uid": "$datasource"
        },
        "definition": "label_values(replication_latency_replication_latency_ms{project_name=\"$project\"}, target)",
        "hide": 0,
        "includeAll": true,
        "label": "Target",
        "multi": false,
        "name": "target",
        "options": [],
        "query": "label_values(replication_latency_replication_latency_ms{project_name=\"$project\",cluster=\"$cluster\"}, target)",
        "refresh": 2,
        "regex": "",
        "skipUrlSync": false,
        "sort": 0,
        "type": "query",
        "useTags": false
      },
      {
        "current": {
          "selected": true,
          "text": [
            "All"
          ],
          "value": [
            "$__all"
          ]
        },
        "datasource": {
          "type": "prometheus",
          "uid": "$datasource"
        },
        "definition": "label_values(replication_latency_replication_latency_ms{project_name=\"$project\"}, topic)",
        "hide": 0,
        "includeAll": true,
        "label": "Topic",
        "multi": true,
        "name": "topic",
        "options": [],
        "query": "label_values(replication_latency_replication_latency_ms{project_name=\"$project\",cluster=\"$cluster\"}, topic)",
        "refresh": 2,
        "regex": "",
        "skipUrlSync": false,
        "sort": 0,
        "type": "query",
        "useTags": false
      },
      {
        "current": {
          "selected": true,
          "text": [
            "All"
          ],
          "value": [
            "$__all"
          ]
        },
        "datasource": {
          "type": "prometheus",
          "uid": "$datasource"
        },
        "definition": "label_values(java_Memory_HeapMemoryUsage_init{project_name=\"$project\"}, url)",
        "hide": 0,
        "includeAll": true,
        "label": "Host",
        "multi": true,
        "name": "host",
        "options": [],
        "query": "label_values(java_Memory_HeapMemoryUsage_init{project_name=\"$project\",cluster=\"$cluster\"}, url)",
        "refresh": 1,
        "regex": "",
        "skipUrlSync": false,
        "sort": 0,
        "type": "query",
        "useTags": false
      }
    ]
  },
  "time": {
    "from": "now-30m",
    "to": "now"
  },
  "timepicker": {
    "refresh_intervals": [
      "1s",
      "2s",
      "5s",
      "10s",
      "30s",
      "1m",
      "5m",
      "15m",
      "30m",
      "1h",
      "2h",
      "1d"
    ]
  },
  "timezone": "browser",
  "title": "Kafka Mirror Maker Monitoring",
  "version": 1483
}